pptx_builder/__init__.py
pptx_builder/__main__.py
pptx_builder_from_yaml-0.0.4.dist-info/LICENSE
pptx_builder_from_yaml-0.0.4.dist-info/METADATA
pptx_builder_from_yaml-0.0.4.dist-info/WHEEL
pptx_builder_from_yaml-0.0.4.dist-info/entry_points.txt
pptx_builder_from_yaml-0.0.4.dist-info/top_level.txt
pptx_builder_from_yaml-0.0.4.dist-info/RECORD
