Metadata-Version: 2.1
Name: pptx-builder-from-yaml
Version: 0.0.4
Summary: CLI to generate powerpoint slides from simple yaml file[s]
Home-page: https://github.com/sukujgrg/pptx-builder-from-yaml
Author: Suku John George
Author-email: sukujgrg@gmail.com
License: MIT
Platform: UNKNOWN
Classifier: Programming Language :: Python :: 3
Classifier: Operating System :: OS Independent
Requires-Python: >=3.4
Requires-Dist: click (==7.0)
Requires-Dist: python-pptx (==0.6.16)
Requires-Dist: PyYAML (==3.13)
Requires-Dist: jsonschema (==2.6.0)
